.gitignore
CODE_OF_CONDUCT.md
LICENSE.txt
MANIFEST.in
README.md
RELIC-INFO
pdk.cgi
setup.cfg
setup.py
doc/Makefile
doc/source_for_diagrams.ppt
doc/misc/databases
doc/misc/junit_notes
doc/source/adding_runners.rst
doc/source/complex_dfd.png
doc/source/conf.py
doc/source/database.rst
doc/source/database_mysql.rst
doc/source/database_sqlserver.rst
doc/source/demo.rst
doc/source/environment.rst
doc/source/example_filetest.py
doc/source/example_testfunction.py
doc/source/faq.rst
doc/source/file_format.rst
doc/source/helper_exml.rst
doc/source/helper_json.rst
doc/source/helper_parameterized.rst
doc/source/helper_reference.rst
doc/source/helper_run.rst
doc/source/helper_testfn.rst
doc/source/helpers.rst
doc/source/index.rst
doc/source/install.rst
doc/source/intro.old.rst
doc/source/intro.rst
doc/source/notes
doc/source/okfile.rst
doc/source/pdk_aware.rst
doc/source/programming.rst
doc/source/programming_db.rst
doc/source/report_fields.rst
doc/source/report_flow.png
doc/source/run_tests.rst
doc/source/runner_fctx.rst
doc/source/runner_maker.rst
doc/source/runner_minipyt.rst
doc/source/runner_nose.rst
doc/source/runner_pytest.rst
doc/source/runner_regtest.rst
doc/source/runner_run.rst
doc/source/runner_shell_runner.rst
doc/source/runner_shunit2.rst
doc/source/runner_unit2.rst
doc/source/runners.rst
doc/source/screen1.html
doc/source/screen2.html
doc/source/screen3.html
doc/source/screen4.html
doc/source/simple_dfd.png
doc/source/testing_pandokia.rst
doc/source/tools.rst
doc/source/vocabulary.rst
extras/check_everywhere
extras/setimages.py
extras/patches/shunit2.README
extras/patches/shunit2.patch
extras/patches/shunit2_plugin_example
extras/patches/shunit2_test.patch
extras/stsci/README
extras/stsci/config.py
extras/stsci/top_level.html
images/delta.png
images/papa.png
images/sienna.jpg
images/sienna.png
pandokia/__init__.py
pandokia/check_expected.py
pandokia/chronic.py
pandokia/cleaner.py
pandokia/common.py
pandokia/contact_notify.py
pandokia/contact_notify_select.py
pandokia.egg-info/PKG-INFO
pandokia.egg-info/SOURCES.txt
pandokia.egg-info/dependency_links.txt
pandokia.egg-info/entry_points.txt
pandokia.egg-info/not-zip-safe
pandokia.egg-info/top_level.txt
