Metadata-Version: 1.1
Name: pandokia
Version: 2.3.0
Summary: Pandokia - a test management and reporting system
Home-page: http://ssb.stsci.edu/testing/
Author: Mark Sienkiewicz, Vicki Laidler
Author-email: help@stsci.edu
License: BSD
Platform: Posix
Platform: MacOS X
Classifier: Development Status :: 5 - Production/Stable
Classifier: Environment :: Console
Classifier: Environment :: Web Environment
Classifier: Intended Audience :: Developers
Classifier: License :: OSI Approved :: BSD License
Classifier: Natural Language :: English
Classifier: Operating System :: POSIX
Classifier: Operating System :: MacOS :: MacOS X
Classifier: Operating System :: Unix
Classifier: Programming Language :: Python :: 2.6
Classifier: Programming Language :: Python :: 2.7
Classifier: Topic :: Software Development :: Quality Assurance
Classifier: Topic :: Software Development :: Testing
